Workbook

Sheet 收入成本预算汇总表
A1: 部门 | B1: 业务分类 | C1: 营业收入(含税) | D1: 收入净额 | E1: 固定成本合计 | F1: 变动成本合计 | G1: 预算业务说明 | H1: 人工成本 | I1: 折旧摊销 | J1: 差旅费 | K1: 会议费 | L1: 业务招待费 | M1: 培训费 | N1: 办公费 | O1: 后勤服务费 | P1: 交通运输费 | Q1: 生产物料费 | R1: 业务支持费-技术配置 | S1: 业务支持费-其他 | T1: 租赁费 | U1: 物流费 | V1: 协会会员费 | W1: 房屋装修及维修费 | X1: 水费 | Y1: 电费 | Z1: 环境保护费 | AA1: 咨询费
A2: 安全运行部 | B2: 安全评估 | C2: =SUMIFS(市场项目预算明细!H:H,市场项目预算明细!$A:$A,$A2,市场项目预算明细!$B:$B,$B2) -> 171.3 | D2: =SUMIFS(市场项目预算明细!I:I,市场项目预算明细!$A:$A,$A2,市场项目预算明细!$B:$B,$B2) -> 161.6 | E2: =H2+I2 -> 19.51 | F2: =SUM(J2:Z2) -> 174.634 | G2: 安全评估类项目合计 | H2: =SUMIFS(市场项目预算明细!O:O,市场项目预算明细!$A:$A,$A2,市场项目预算明细!$B:$B,$B2) -> 12.68 | I2: =SUMIFS(市场项目预算明细!P:P,市场项目预算明细!$A:$A,$A2,市场项目预算明细!$B:$B,$B2) -> 6.83 | J2: =SUMIFS(市场项目预算明细!S:S,市场项目预算明细!$A:$A,$A2,市场项目预算明细!$B:$B,$B2) -> 6.464 | K2: =SUMIFS(市场项目预算明细!T:T,市场项目预算明细!$A:$A,$A2,市场项目预算明细!$B:$B,$B2) -> 0.65 | L2: =SUMIFS(市场项目预算明细!U:U,市场项目预算明细!$A:$A,$A2,市场项目预算明细!$B:$B,$B2) -> 0 | M2: =SUMIFS(市场项目预算明细!V:V,市场项目预算明细!$A:$A,$A2,市场项目预算明细!$B:$B,$B2) -> 0.32 | N2: =SUMIFS(市场项目预算明细!W:W,市场项目预算明细!$A:$A,$A2,市场项目预算明细!$B:$B,$B2) -> 0.32 | O2: =SUMIFS(市场项目预算明细!X:X,市场项目预算明细!$A:$A,$A2,市场项目预算明细!$B:$B,$B2) -> 0.26 | P2: =SUMIFS(市场项目预算明细!Y:Y,市场项目预算明细!$A:$A,$A2,市场项目预算明细!$B:$B,$B2) -> 0.97 | Q2: =SUMIFS(市场项目预算明细!Z:Z,市场项目预算明细!$A:$A,$A2,市场项目预算明细!$B:$B,$B2) -> 19.5 | R2: =SUMIFS(市场项目预算明细!AL:AL,市场项目预算明细!$A:$A,$A2,市场项目预算明细!$B:$B,$B2) -> 129.05 | S2: =SUMIFS(市场项目预算明细!AA:AA,市场项目预算明细!$A:$A,$A2,市场项目预算明细!$B:$B,$B2) -> 16.26 | T2: =SUMIFS(市场项目预算明细!AB:AB,市场项目预算明细!$A:$A,$A2,市场项目预算明细!$B:$B,$B2) -> 0.65 | U2: =SUMIFS(市场项目预算明细!AC:AC,市场项目预算明细!$A:$A,$A2,市场项目预算明细!$B:$B,$B2) -> 0.19 | V2: =SUMIFS(市场项目预算明细!AD:AD,市场项目预算明细!$A:$A,$A2,市场项目预算明细!$B:$B,$B2) -> 0 | W2: =SUMIFS(市场项目预算明细!AE:AE,市场项目预算明细!$A:$A,$A2,市场项目预算明细!$B:$B,$B2) -> 0 | X2: =SUMIFS(市场项目预算明细!AF:AF,市场项目预算明细!$A:$A,$A2,市场项目预算明细!$B:$B,$B2) -> 0 | Y2: =SUMIFS(市场项目预算明细!AG:AG,市场项目预算明细!$A:$A,$A2,市场项目预算明细!$B:$B,$B2) -> 0 | Z2: =SUMIFS(市场项目预算明细!AH:AH,市场项目预算明细!$A:$A,$A2,市场项目预算明细!$B:$B,$B2) -> 0 | AA2: =SUMIFS(市场项目预算明细!AI:AI,市场项目预算明细!$A:$A,$A2,市场项目预算明细!$B:$B,$B2) -> 0
A3: 安全运行部 | B3: 部门公共费用 | C3: 0 | D3: 0 | E3: 0 | F3: =SUMIFS(部门公共费用明细!G:G,部门公共费用明细!A:A,$A3) -> 5 | G3: 部门公共费用 | H3: 0 | I3: 0 | J3: 0 | K3: 0 | L3: 0 | M3: =SUMIFS(部门公共费用明细!G:G,部门公共费用明细!A:A,$A3,部门公共费用明细!B:B,"培训费") -> 1.42 | N3: =SUMIFS(部门公共费用明细!G:G,部门公共费用明细!A:A,$A3,部门公共费用明细!B:B,"办公费") -> 2.36 | O3: 0 | P3: 0 | Q3: 0 | R3: 0 | S3: 0 | T3: 0 | U3: 0 | V3: 0 | W3: 0 | X3: =SUMIFS(部门公共费用明细!G:G,部门公共费用明细!A:A,$A3,部门公共费用明细!B:B,"水费") -> 0.47 | Y3: =SUMIFS(部门公共费用明细!G:G,部门公共费用明细!A:A,$A3,部门公共费用明细!B:B,"电费") -> 0.75 | Z3: 0 | AA3: 0
A4: 安全运行部 | B4: 概率安全分析 | C4: =SUMIFS(市场项目预算明细!H:H,市场项目预算明细!$A:$A,$A4,市场项目预算明细!$B:$B,$B4) -> 157.09 | D4: =SUMIFS(市场项目预算明细!I:I,市场项目预算明细!$A:$A,$A4,市场项目预算明细!$B:$B,$B4) -> 148.2 | E4: =H4+I4 -> 17.84 | F4: =SUM(J4:Z4) -> 162.898 | G4: 概率安全分析类项目合计 | H4: =SUMIFS(市场项目预算明细!O:O,市场项目预算明细!$A:$A,$A4,市场项目预算明细!$B:$B,$B4) -> 11.59 | I4: =SUMIFS(市场项目预算明细!P:P,市场项目预算明细!$A:$A,$A4,市场项目预算明细!$B:$B,$B4) -> 6.25 | J4: =SUMIFS(市场项目预算明细!S:S,市场项目预算明细!$A:$A,$A4,市场项目预算明细!$B:$B,$B4) -> 5.928 | K4: =SUMIFS(市场项目预算明细!T:T,市场项目预算明细!$A:$A,$A4,市场项目预算明细!$B:$B,$B4) -> 0.6 | L4: =SUMIFS(市场项目预算明细!U:U,市场项目预算明细!$A:$A,$A4,市场项目预算明细!$B:$B,$B4) -> 0 | M4: =SUMIFS(市场项目预算明细!V:V,市场项目预算明细!$A:$A,$A4,市场项目预算明细!$B:$B,$B4) -> 0.29 | N4: =SUMIFS(市场项目预算明细!W:W,市场项目预算明细!$A:$A,$A4,市场项目预算明细!$B:$B,$B4) -> 0.29 | O4: =SUMIFS(市场项目预算明细!X:X,市场项目预算明细!$A:$A,$A4,市场项目预算明细!$B:$B,$B4) -> 0.23 | P4: =SUMIFS(市场项目预算明细!Y:Y,市场项目预算明细!$A:$A,$A4,市场项目预算明细!$B:$B,$B4) -> 0.89 | Q4: =SUMIFS(市场项目预算明细!Z:Z,市场项目预算明细!$A:$A,$A4,市场项目预算明细!$B:$B,$B4) -> 17.9 | R4: =SUMIFS(市场项目预算明细!AL:AL,市场项目预算明细!$A:$A,$A4,市场项目预算明细!$B:$B,$B4) -> 121.13 | S4: =SUMIFS(市场项目预算明细!AA:AA,市场项目预算明细!$A:$A,$A4,市场项目预算明细!$B:$B,$B4) -> 14.86 | T4: =SUMIFS(市场项目预算明细!AB:AB,市场项目预算明细!$A:$A,$A4,市场项目预算明细!$B:$B,$B4) -> 0.6 | U4: =SUMIFS(市场项目预算明细!AC:AC,市场项目预算明细!$A:$A,$A4,市场项目预算明细!$B:$B,$B4) -> 0.18 | V4: =SUMIFS(市场项目预算明细!AD:AD,市场项目预算明细!$A:$A,$A4,市场项目预算明细!$B:$B,$B4) -> 0 | W4: =SUMIFS(市场项目预算明细!AE:AE,市场项目预算明细!$A:$A,$A4,市场项目预算明细!$B:$B,$B4) -> 0 | X4: =SUMIFS(市场项目预算明细!AF:AF,市场项目预算明细!$A:$A,$A4,市场项目预算明细!$B:$B,$B4) -> 0 | Y4: =SUMIFS(市场项目预算明细!AG:AG,市场项目预算明细!$A:$A,$A4,市场项目预算明细!$B:$B,$B4) -> 0 | Z4: =SUMIFS(市场项目预算明细!AH:AH,市场项目预算明细!$A:$A,$A4,市场项目预算明细!$B:$B,$B4) -> 0 | AA4: =SUMIFS(市场项目预算明细!AI:AI,市场项目预算明细!$A:$A,$A4,市场项目预算明细!$B:$B,$B4) -> 0
A5: 安全运行部 | B5: 灾害防护 | C5: =SUMIFS(市场项目预算明细!H:H,市场项目预算明细!$A:$A,$A5,市场项目预算明细!$B:$B,$B5) -> 154.12 | D5: =SUMIFS(市场项目预算明细!I:I,市场项目预算明细!$A:$A,$A5,市场项目预算明细!$B:$B,$B5) -> 145.4 | E5: =H5+I5 -> 17.36 | F5: =SUM(J5:Z5) -> 80.356 | G5: 灾害防护类项目合计 | H5: =SUMIFS(市场项目预算明细!O:O,市场项目预算明细!$A:$A,$A5,市场项目预算明细!$B:$B,$B5) -> 11.29 | I5: =SUMIFS(市场项目预算明细!P:P,市场项目预算明细!$A:$A,$A5,市场项目预算明细!$B:$B,$B5) -> 6.07 | J5: =SUMIFS(市场项目预算明细!S:S,市场项目预算明细!$A:$A,$A5,市场项目预算明细!$B:$B,$B5) -> 5.816 | K5: =SUMIFS(市场项目预算明细!T:T,市场项目预算明细!$A:$A,$A5,市场项目预算明细!$B:$B,$B5) -> 0.58 | L5: =SUMIFS(市场项目预算明细!U:U,市场项目预算明细!$A:$A,$A5,市场项目预算明细!$B:$B,$B5) -> 0 | M5: =SUMIFS(市场项目预算明细!V:V,市场项目预算明细!$A:$A,$A5,市场项目预算明细!$B:$B,$B5) -> 0.3 | N5: =SUMIFS(市场项目预算明细!W:W,市场项目预算明细!$A:$A,$A5,市场项目预算明细!$B:$B,$B5) -> 0.3 | O5: =SUMIFS(市场项目预算明细!X:X,市场项目预算明细!$A:$A,$A5,市场项目预算明细!$B:$B,$B5) -> 0.24 | P5: =SUMIFS(市场项目预算明细!Y:Y,市场项目预算明细!$A:$A,$A5,市场项目预算明细!$B:$B,$B5) -> 0.87 | Q5: =SUMIFS(市场项目预算明细!Z:Z,市场项目预算明细!$A:$A,$A5,市场项目预算明细!$B:$B,$B5) -> 17.4 | R5: =SUMIFS(市场项目预算明细!AL:AL,市场项目预算明细!$A:$A,$A5,市场项目预算明细!$B:$B,$B5) -> 39.62 | S5: =SUMIFS(市场项目预算明细!AA:AA,市场项目预算明细!$A:$A,$A5,市场项目预算明细!$B:$B,$B5) -> 14.48 | T5: =SUMIFS(市场项目预算明细!AB:AB,市场项目预算明细!$A:$A,$A5,市场项目预算明细!$B:$B,$B5) -> 0.58 | U5: =SUMIFS(市场项目预算明细!AC:AC,市场项目预算明细!$A:$A,$A5,市场项目预算明细!$B:$B,$B5) -> 0.17 | V5: =SUMIFS(市场项目预算明细!AD:AD,市场项目预算明细!$A:$A,$A5,市场项目预算明细!$B:$B,$B5) -> 0 | W5: =SUMIFS(市场项目预算明细!AE:AE,市场项目预算明细!$A:$A,$A5,市场项目预算明细!$B:$B,$B5) -> 0 | X5: =SUMIFS(市场项目预算明细!AF:AF,市场项目预算明细!$A:$A,$A5,市场项目预算明细!$B:$B,$B5) -> 0 | Y5: =SUMIFS(市场项目预算明细!AG:AG,市场项目预算明细!$A:$A,$A5,市场项目预算明细!$B:$B,$B5) -> 0 | Z5: =SUMIFS(市场项目预算明细!AH:AH,市场项目预算明细!$A:$A,$A5,市场项目预算明细!$B:$B,$B5) -> 0 | AA5: =SUMIFS(市场项目预算明细!AI:AI,市场项目预算明细!$A:$A,$A5,市场项目预算明细!$B:$B,$B5) -> 0
A6: 技术部 | B6: 新技术应用 | C6: =SUMIFS(市场项目预算明细!H:H,市场项目预算明细!$A:$A,$A6,市场项目预算明细!$B:$B,$B6) -> 214.44 | D6: =SUMIFS(市场项目预算明细!I:I,市场项目预算明细!$A:$A,$A6,市场项目预算明细!$B:$B,$B6) -> 202.3 | E6: =H6+I6 -> 16 | F6: =SUM(J6:Z6) -> 352.642 | G6: 新技术应用类项目合计 | H6: =SUMIFS(市场项目预算明细!O:O,市场项目预算明细!$A:$A,$A6,市场项目预算明细!$B:$B,$B6) -> 10.41 | I6: =SUMIFS(市场项目预算明细!P:P,市场项目预算明细!$A:$A,$A6,市场项目预算明细!$B:$B,$B6) -> 5.59 | J6: =SUMIFS(市场项目预算明细!S:S,市场项目预算明细!$A:$A,$A6,市场项目预算明细!$B:$B,$B6) -> 8.092 | K6: =SUMIFS(市场项目预算明细!T:T,市场项目预算明细!$A:$A,$A6,市场项目预算明细!$B:$B,$B6) -> 0.53 | L6: =SUMIFS(市场项目预算明细!U:U,市场项目预算明细!$A:$A,$A6,市场项目预算明细!$B:$B,$B6) -> 0 | M6: =SUMIFS(市场项目预算明细!V:V,市场项目预算明细!$A:$A,$A6,市场项目预算明细!$B:$B,$B6) -> 0.27 | N6: =SUMIFS(市场项目预算明细!W:W,市场项目预算明细!$A:$A,$A6,市场项目预算明细!$B:$B,$B6) -> 0.27 | O6: =SUMIFS(市场项目预算明细!X:X,市场项目预算明细!$A:$A,$A6,市场项目预算明细!$B:$B,$B6) -> 0.21 | P6: =SUMIFS(市场项目预算明细!Y:Y,市场项目预算明细!$A:$A,$A6,市场项目预算明细!$B:$B,$B6) -> 0.8 | Q6: =SUMIFS(市场项目预算明细!Z:Z,市场项目预算明细!$A:$A,$A6,市场项目预算明细!$B:$B,$B6) -> 16 | R6: =SUMIFS(市场项目预算明细!AL:AL,市场项目预算明细!$A:$A,$A6,市场项目预算明细!$B:$B,$B6) -> 312.45 | S6: =SUMIFS(市场项目预算明细!AA:AA,市场项目预算明细!$A:$A,$A6,市场项目预算明细!$B:$B,$B6) -> 13.33 | T6: =SUMIFS(市场项目预算明细!AB:AB,市场项目预算明细!$A:$A,$A6,市场项目预算明细!$B:$B,$B6) -> 0.53 | U6: =SUMIFS(市场项目预算明细!AC:AC,市场项目预算明细!$A:$A,$A6,市场项目预算明细!$B:$B,$B6) -> 0.16 | V6: =SUMIFS(市场项目预算明细!AD:AD,市场项目预算明细!$A:$A,$A6,市场项目预算明细!$B:$B,$B6) -> 0 | W6: =SUMIFS(市场项目预算明细!AE:AE,市场项目预算明细!$A:$A,$A6,市场项目预算明细!$B:$B,$B6) -> 0 | X6: =SUMIFS(市场项目预算明细!AF:AF,市场项目预算明细!$A:$A,$A6,市场项目预算明细!$B:$B,$B6) -> 0 | Y6: =SUMIFS(市场项目预算明细!AG:AG,市场项目预算明细!$A:$A,$A6,市场项目预算明细!$B:$B,$B6) -> 0 | Z6: =SUMIFS(市场项目预算明细!AH:AH,市场项目预算明细!$A:$A,$A6,市场项目预算明细!$B:$B,$B6) -> 0 | AA6: =SUMIFS(市场项目预算明细!AI:AI,市场项目预算明细!$A:$A,$A6,市场项目预算明细!$B:$B,$B6) -> 0
A7: 技术部 | B7: 部门公共费用 | C7: 0 | D7: 0 | E7: 0 | F7: =SUMIFS(部门公共费用明细!G:G,部门公共费用明细!A:A,$A7) -> 5 | G7: 部门公共费用 | H7: 0 | I7: 0 | J7: 0 | K7: 0 | L7: 0 | M7: =SUMIFS(部门公共费用明细!G:G,部门公共费用明细!A:A,$A7,部门公共费用明细!B:B,"培训费") -> 1.42 | N7: =SUMIFS(部门公共费用明细!G:G,部门公共费用明细!A:A,$A7,部门公共费用明细!B:B,"办公费") -> 2.36 | O7: 0 | P7: 0 | Q7: 0 | R7: 0 | S7: 0 | T7: 0 | U7: 0 | V7: 0 | W7: 0 | X7: =SUMIFS(部门公共费用明细!G:G,部门公共费用明细!A:A,$A7,部门公共费用明细!B:B,"水费") -> 0.47 | Y7: =SUMIFS(部门公共费用明细!G:G,部门公共费用明细!A:A,$A7,部门公共费用明细!B:B,"电费") -> 0.75 | Z7: 0 | AA7: 0
A8: 技术部 | B8: 热能动力研究 | C8: =SUMIFS(市场项目预算明细!H:H,市场项目预算明细!$A:$A,$A8,市场项目预算明细!$B:$B,$B8) -> 207.86 | D8: =SUMIFS(市场项目预算明细!I:I,市场项目预算明细!$A:$A,$A8,市场项目预算明细!$B:$B,$B8) -> 196.1 | E8: =H8+I8 -> 15.38 | F8: =SUM(J8:Z8) -> 340.994 | G8: 热能动力研究类项目合计 | H8: =SUMIFS(市场项目预算明细!O:O,市场项目预算明细!$A:$A,$A8,市场项目预算明细!$B:$B,$B8) -> 10 | I8: =SUMIFS(市场项目预算明细!P:P,市场项目预算明细!$A:$A,$A8,市场项目预算明细!$B:$B,$B8) -> 5.38 | J8: =SUMIFS(市场项目预算明细!S:S,市场项目预算明细!$A:$A,$A8,市场项目预算明细!$B:$B,$B8) -> 7.844 | K8: =SUMIFS(市场项目预算明细!T:T,市场项目预算明细!$A:$A,$A8,市场项目预算明细!$B:$B,$B8) -> 0.51 | L8: =SUMIFS(市场项目预算明细!U:U,市场项目预算明细!$A:$A,$A8,市场项目预算明细!$B:$B,$B8) -> 0 | M8: =SUMIFS(市场项目预算明细!V:V,市场项目预算明细!$A:$A,$A8,市场项目预算明细!$B:$B,$B8) -> 0.26 | N8: =SUMIFS(市场项目预算明细!W:W,市场项目预算明细!$A:$A,$A8,市场项目预算明细!$B:$B,$B8) -> 0.26 | O8: =SUMIFS(市场项目预算明细!X:X,市场项目预算明细!$A:$A,$A8,市场项目预算明细!$B:$B,$B8) -> 0.21 | P8: =SUMIFS(市场项目预算明细!Y:Y,市场项目预算明细!$A:$A,$A8,市场项目预算明细!$B:$B,$B8) -> 0.77 | Q8: =SUMIFS(市场项目预算明细!Z:Z,市场项目预算明细!$A:$A,$A8,市场项目预算明细!$B:$B,$B8) -> 15.4 | R8: =SUMIFS(市场项目预算明细!AL:AL,市场项目预算明细!$A:$A,$A8,市场项目预算明细!$B:$B,$B8) -> 302.26 | S8: =SUMIFS(市场项目预算明细!AA:AA,市场项目预算明细!$A:$A,$A8,市场项目预算明细!$B:$B,$B8) -> 12.82 | T8: =SUMIFS(市场项目预算明细!AB:AB,市场项目预算明细!$A:$A,$A8,市场项目预算明细!$B:$B,$B8) -> 0.51 | U8: =SUMIFS(市场项目预算明细!AC:AC,市场项目预算明细!$A:$A,$A8,市场项目预算明细!$B:$B,$B8) -> 0.15 | V8: =SUMIFS(市场项目预算明细!AD:AD,市场项目预算明细!$A:$A,$A8,市场项目预算明细!$B:$B,$B8) -> 0 | W8: =SUMIFS(市场项目预算明细!AE:AE,市场项目预算明细!$A:$A,$A8,市场项目预算明细!$B:$B,$B8) -> 0 | X8: =SUMIFS(市场项目预算明细!AF:AF,市场项目预算明细!$A:$A,$A8,市场项目预算明细!$B:$B,$B8) -> 0 | Y8: =SUMIFS(市场项目预算明细!AG:AG,市场项目预算明细!$A:$A,$A8,市场项目预算明细!$B:$B,$B8) -> 0 | Z8: =SUMIFS(市场项目预算明细!AH:AH,市场项目预算明细!$A:$A,$A8,市场项目预算明细!$B:$B,$B8) -> 0 | AA8: =SUMIFS(市场项目预算明细!AI:AI,市场项目预算明细!$A:$A,$A8,市场项目预算明细!$B:$B,$B8) -> 0
A9: 技术部 | B9: 经验反馈改进 | C9: =SUMIFS(市场项目预算明细!H:H,市场项目预算明细!$A:$A,$A9,市场项目预算明细!$B:$B,$B9) -> 225.89 | D9: =SUMIFS(市场项目预算明细!I:I,市场项目预算明细!$A:$A,$A9,市场项目预算明细!$B:$B,$B9) -> 213.1 | E9: =H9+I9 -> 16.82 | F9: =SUM(J9:Z9) -> 223.104 | G9: 经验反馈改进类项目合计 | H9: =SUMIFS(市场项目预算明细!O:O,市场项目预算明细!$A:$A,$A9,市场项目预算明细!$B:$B,$B9) -> 10.93 | I9: =SUMIFS(市场项目预算明细!P:P,市场项目预算明细!$A:$A,$A9,市场项目预算明细!$B:$B,$B9) -> 5.89 | J9: =SUMIFS(市场项目预算明细!S:S,市场项目预算明细!$A:$A,$A9,市场项目预算明细!$B:$B,$B9) -> 8.524 | K9: =SUMIFS(市场项目预算明细!T:T,市场项目预算明细!$A:$A,$A9,市场项目预算明细!$B:$B,$B9) -> 0.56 | L9: =SUMIFS(市场项目预算明细!U:U,市场项目预算明细!$A:$A,$A9,市场项目预算明细!$B:$B,$B9) -> 0 | M9: =SUMIFS(市场项目预算明细!V:V,市场项目预算明细!$A:$A,$A9,市场项目预算明细!$B:$B,$B9) -> 0.28 | N9: =SUMIFS(市场项目预算明细!W:W,市场项目预算明细!$A:$A,$A9,市场项目预算明细!$B:$B,$B9) -> 0.28 | O9: =SUMIFS(市场项目预算明细!X:X,市场项目预算明细!$A:$A,$A9,市场项目预算明细!$B:$B,$B9) -> 0.22 | P9: =SUMIFS(市场项目预算明细!Y:Y,市场项目预算明细!$A:$A,$A9,市场项目预算明细!$B:$B,$B9) -> 0.85 | Q9: =SUMIFS(市场项目预算明细!Z:Z,市场项目预算明细!$A:$A,$A9,市场项目预算明细!$B:$B,$B9) -> 16.8 | R9: =SUMIFS(市场项目预算明细!AL:AL,市场项目预算明细!$A:$A,$A9,市场项目预算明细!$B:$B,$B9) -> 180.84 | S9: =SUMIFS(市场项目预算明细!AA:AA,市场项目预算明细!$A:$A,$A9,市场项目预算明细!$B:$B,$B9) -> 14.01 | T9: =SUMIFS(市场项目预算明细!AB:AB,市场项目预算明细!$A:$A,$A9,市场项目预算明细!$B:$B,$B9) -> 0.56 | U9: =SUMIFS(市场项目预算明细!AC:AC,市场项目预算明细!$A:$A,$A9,市场项目预算明细!$B:$B,$B9) -> 0.18 | V9: =SUMIFS(市场项目预算明细!AD:AD,市场项目预算明细!$A:$A,$A9,市场项目预算明细!$B:$B,$B9) -> 0 | W9: =SUMIFS(市场项目预算明细!AE:AE,市场项目预算明细!$A:$A,$A9,市场项目预算明细!$B:$B,$B9) -> 0 | X9: =SUMIFS(市场项目预算明细!AF:AF,市场项目预算明细!$A:$A,$A9,市场项目预算明细!$B:$B,$B9) -> 0 | Y9: =SUMIFS(市场项目预算明细!AG:AG,市场项目预算明细!$A:$A,$A9,市场项目预算明细!$B:$B,$B9) -> 0 | Z9: =SUMIFS(市场项目预算明细!AH:AH,市场项目预算明细!$A:$A,$A9,市场项目预算明细!$B:$B,$B9) -> 0 | AA9: =SUMIFS(市场项目预算明细!AI:AI,市场项目预算明细!$A:$A,$A9,市场项目预算明细!$B:$B,$B9) -> 0
A10: 设备管理部 | B10: 设备维护 | C10: =SUMIFS(市场项目预算明细!H:H,市场项目预算明细!$A:$A,$A10,市场项目预算明细!$B:$B,$B10) -> 791.39 | D10: =SUMIFS(市场项目预算明细!I:I,市场项目预算明细!$A:$A,$A10,市场项目预算明细!$B:$B,$B10) -> 746.6 | E10: =H10+I10 -> 75.24 | F10: =SUM(J10:Z10) -> 218.364 | G10: 设备维护类项目合计 | H10: =SUMIFS(市场项目预算明细!O:O,市场项目预算明细!$A:$A,$A10,市场项目预算明细!$B:$B,$B10) -> 48.91 | I10: =SUMIFS(市场项目预算明细!P:P,市场项目预算明细!$A:$A,$A10,市场项目预算明细!$B:$B,$B10) -> 26.33 | J10: =SUMIFS(市场项目预算明细!S:S,市场项目预算明细!$A:$A,$A10,市场项目预算明细!$B:$B,$B10) -> 29.864 | K10: =SUMIFS(市场项目预算明细!T:T,市场项目预算明细!$A:$A,$A10,市场项目预算明细!$B:$B,$B10) -> 2.5 | L10: =SUMIFS(市场项目预算明细!U:U,市场项目预算明细!$A:$A,$A10,市场项目预算明细!$B:$B,$B10) -> 0 | M10: =SUMIFS(市场项目预算明细!V:V,市场项目预算明细!$A:$A,$A10,市场项目预算明细!$B:$B,$B10) -> 1.25 | N10: =SUMIFS(市场项目预算明细!W:W,市场项目预算明细!$A:$A,$A10,市场项目预算明细!$B:$B,$B10) -> 1.25 | O10: =SUMIFS(市场项目预算明细!X:X,市场项目预算明细!$A:$A,$A10,市场项目预算明细!$B:$B,$B10) -> 1 | P10: =SUMIFS(市场项目预算明细!Y:Y,市场项目预算明细!$A:$A,$A10,市场项目预算明细!$B:$B,$B10) -> 3.76 | Q10: =SUMIFS(市场项目预算明细!Z:Z,市场项目预算明细!$A:$A,$A10,市场项目预算明细!$B:$B,$B10) -> 75.2 | R10: =SUMIFS(市场项目预算明细!AL:AL,市场项目预算明细!$A:$A,$A10,市场项目预算明细!$B:$B,$B10) -> 37.58 | S10: =SUMIFS(市场项目预算明细!AA:AA,市场项目预算明细!$A:$A,$A10,市场项目预算明细!$B:$B,$B10) -> 62.71 | T10: =SUMIFS(市场项目预算明细!AB:AB,市场项目预算明细!$A:$A,$A10,市场项目预算明细!$B:$B,$B10) -> 2.5 | U10: =SUMIFS(市场项目预算明细!AC:AC,市场项目预算明细!$A:$A,$A10,市场项目预算明细!$B:$B,$B10) -> 0.75 | V10: =SUMIFS(市场项目预算明细!AD:AD,市场项目预算明细!$A:$A,$A10,市场项目预算明细!$B:$B,$B10) -> 0 | W10: =SUMIFS(市场项目预算明细!AE:AE,市场项目预算明细!$A:$A,$A10,市场项目预算明细!$B:$B,$B10) -> 0 | X10: =SUMIFS(市场项目预算明细!AF:AF,市场项目预算明细!$A:$A,$A10,市场项目预算明细!$B:$B,$B10) -> 0 | Y10: =SUMIFS(市场项目预算明细!AG:AG,市场项目预算明细!$A:$A,$A10,市场项目预算明细!$B:$B,$B10) -> 0 | Z10: =SUMIFS(市场项目预算明细!AH:AH,市场项目预算明细!$A:$A,$A10,市场项目预算明细!$B:$B,$B10) -> 0 | AA10: =SUMIFS(市场项目预算明细!AI:AI,市场项目预算明细!$A:$A,$A10,市场项目预算明细!$B:$B,$B10) -> 0
A11: 设备管理部 | B11: 部门公共费用 | C11: 0 | D11: 0 | E11: 0 | F11: =SUMIFS(部门公共费用明细!G:G,部门公共费用明细!A:A,$A11) -> 5 | G11: 部门公共费用 | H11: 0 | I11: 0 | J11: 0 | K11: 0 | L11: 0 | M11: =SUMIFS(部门公共费用明细!G:G,部门公共费用明细!A:A,$A11,部门公共费用明细!B:B,"培训费") -> 1.42 | N11: =SUMIFS(部门公共费用明细!G:G,部门公共费用明细!A:A,$A11,部门公共费用明细!B:B,"办公费") -> 2.36 | O11: 0 | P11: 0 | Q11: 0 | R11: 0 | S11: 0 | T11: 0 | U11: 0 | V11: 0 | W11: 0 | X11: =SUMIFS(部门公共费用明细!G:G,部门公共费用明细!A:A,$A11,部门公共费用明细!B:B,"水费") -> 0.47 | Y11: =SUMIFS(部门公共费用明细!G:G,部门公共费用明细!A:A,$A11,部门公共费用明细!B:B,"电费") -> 0.75 | Z11: 0 | AA11: 0

Sheet 市场项目预算明细
A1: 部门 | B1: 业务分类 | C1: 项目名称 | D1: 项目编号 | E1: 合同情况 | F1: 客户名称 | G1: 税率 | H1: 含税收入 | I1: 收入净额 | J1: 固定成本合计 | K1: 其中： | L1: 在职人数 | M1: 平均人工成本(万元/月) | N1: 投入人月 | O1: 人工成本 | P1: 折旧成本 | Q1: 可控成本合计 | R1: 其中： | S1: 差旅费 | T1: 会议费 | U1: 业务招待费 | V1: 培训费 | W1: 办公费 | X1: 后勤服务费 | Y1: 交通运输费 | Z1: 生产物料费 | AA1: 业务支持费 | AB1: 租赁费 | AC1: 物流费 | AD1: 协会会员费 | AE1: 房屋装修及维修费 | AF1: 水费 | AG1: 电费 | AH1: 环境保护费 | AI1: 咨询费 | AJ1: 业务支持费-技术配置(人月) | AK1: 业务支持费-技术配置(含税-万) | AL1: 业务支持费-技术配置(净额-万) | AM1: 项目成本合计 | AN1: 毛利率
A2: 设备管理部 | B2: 设备维护 | C2: 设备维护 | D2: PRJ-SB-设备-2024-001 | E2: 已签订 | F2: XX能源集团 | G2: 0.06 | H2: 254.61 | I2: 240.2 | J2: 24.27 | K2: 其中： | L2: 5 | M2: 0.26 | N2: 60 | O2: 15.78 | P2: 8.49 | Q2: 71.008 | R2: 其中： | S2: 9.608 | T2: 0.81 | U2: 0 | V2: 0.4 | W2: 0.4 | X2: 0.32 | Y2: 1.21 | Z2: 24.3 | AA2: 20.23 | AB2: 0.81 | AC2: 0.24 | AD2: 0 | AE2: 0 | AF2: 0 | AG2: 0 | AH2: 0 | AI2: 0 | AJ2: =SUMIFS(技术配置!I:I,技术配置!F:F,$D2) -> 12 | AK2: =SUMIFS(技术配置!L:L,技术配置!F:F,$D2) -> 13.44 | AL2: =SUMIFS(技术配置!M:M,技术配置!F:F,$D2) -> 12.68 | AM2: 95.278 | AN2: =AM2/I2 -> 0.39666112
A3: 设备管理部 | B3: 设备维护 | C3: 设备维护 | D3: PRJ-SB-设备-2025-002 | E3: 已签订 | F3: XX能源集团 | G3: 0.06 | H3: 272.84 | I3: 257.4 | J3: 25.94 | K3: 其中： | L3: 5 | M3: 0.28 | N3: 60 | O3: 16.86 | P3: 9.08 | Q3: 74.756 | R3: 其中： | S3: 10.296 | T3: 0.86 | U3: 0 | V3: 0.43 | W3: 0.43 | X3: 0.35 | Y3: 1.3 | Z3: 25.9 | AA3: 21.62 | AB3: 0.86 | AC3: 0.26 | AD3: 0 | AE3: 0 | AF3: 0 | AG3: 0 | AH3: 0 | AI3: 0 | AJ3: =SUMIFS(技术配置!I:I,技术配置!F:F,$D3) -> 12 | AK3: =SUMIFS(技术配置!L:L,技术配置!F:F,$D3) -> 13.2 | AL3: =SUMIFS(技术配置!M:M,技术配置!F:F,$D3) -> 12.45 | AM3: 100.696 | AN3: =AM3/I3 -> 0.39120435
A4: 设备管理部 | B4: 设备维护 | C4: 设备维护 | D4: PRJ-SB-设备-2025-003 | E4: 已签订 | F4: XX能源集团 | G4: 0.06 | H4: 263.94 | I4: 249 | J4: 25.03 | K4: 其中： | L4: 5 | M4: 0.27 | N4: 60 | O4: 16.27 | P4: 8.76 | Q4: 72.6 | R4: 其中： | S4: 9.96 | T4: 0.83 | U4: 0 | V4: 0.42 | W4: 0.42 | X4: 0.33 | Y4: 1.25 | Z4: 25 | AA4: 20.86 | AB4: 0.83 | AC4: 0.25 | AD4: 0 | AE4: 0 | AF4: 0 | AG4: 0 | AH4: 0 | AI4: 0 | AJ4: =SUMIFS(技术配置!I:I,技术配置!F:F,$D4) -> 12 | AK4: =SUMIFS(技术配置!L:L,技术配置!F:F,$D4) -> 13.2 | AL4: =SUMIFS(技术配置!M:M,技术配置!F:F,$D4) -> 12.45 | AM4: 97.63 | AN4: =AM4/I4 -> 0.39208835
A5: 技术部 | B5: 热能动力研究 | C5: 热能动力研究 | D5: PRJ-JS-热能-2024-001 | E5: 已签订 | F5: XX能源集团 | G5: 0.06 | H5: 66.04 | I5: 62.3 | J5: 4.98 | K5: 其中： | L5: 5 | M5: 0.05 | N5: 60 | O5: 3.24 | P5: 1.74 | Q5: 118.132 | R5: 其中： | S5: 2.492 | T5: 0.17 | U5: 0 | V5: 0.08 | W5: 0.08 | X5: 0.07 | Y5: 0.25 | Z5: 5 | AA5: 4.15 | AB5: 0.17 | AC5: 0.05 | AD5: 0 | AE5: 0 | AF5: 0 | AG5: 0 | AH5: 0 | AI5: 0 | AJ5: =SUMIFS(技术配置!I:I,技术配置!F:F,$D5) -> 36 | AK5: =SUMIFS(技术配置!L:L,技术配置!F:F,$D5) -> 111.96 | AL5: =SUMIFS(技术配置!M:M,技术配置!F:F,$D5) -> 105.62 | AM5: 123.112 | AN5: =AM5/I5 -> 1.9761156
A6: 技术部 | B6: 热能动力研究 | C6: 热能动力研究 | D6: PRJ-JS-热能-2025-002 | E6: 已签订 | F6: XX能源集团 | G6: 0.06 | H6: 70.38 | I6: 66.4 | J6: 5.17 | K6: 其中： | L6: 5 | M6: 0.06 | N6: 60 | O6: 3.36 | P6: 1.81 | Q6: 112.916 | R6: 其中： | S6: 2.656 | T6: 0.17 | U6: 0 | V6: 0.09 | W6: 0.09 | X6: 0.07 | Y6: 0.26 | Z6: 5.2 | AA6: 4.31 | AB6: 0.17 | AC6: 0.05 | AD6: 0 | AE6: 0 | AF6: 0 | AG6: 0 | AH6: 0 | AI6: 0 | AJ6: =SUMIFS(技术配置!I:I,技术配置!F:F,$D6) -> 36 | AK6: =SUMIFS(技术配置!L:L,技术配置!F:F,$D6) -> 105.84 | AL6: =SUMIFS(技术配置!M:M,技术配置!F:F,$D6) -> 99.85 | AM6: 118.086 | AN6: =AM6/I6 -> 1.7784036
A7: 技术部 | B7: 热能动力研究 | C7: 热能动力研究 | D7: PRJ-JS-热能-2025-003 | E7: 已签订 | F7: XX能源集团 | G7: 0.06 | H7: 71.44 | I7: 67.4 | J7: 5.23 | K7: 其中： | L7: 5 | M7: 0.06 | N7: 60 | O7: 3.4 | P7: 1.83 | Q7: 109.946 | R7: 其中： | S7: 2.696 | T7: 0.17 | U7: 0 | V7: 0.09 | W7: 0.09 | X7: 0.07 | Y7: 0.26 | Z7: 5.2 | AA7: 4.36 | AB7: 0.17 | AC7: 0.05 | AD7: 0 | AE7: 0 | AF7: 0 | AG7: 0 | AH7: 0 | AI7: 0 | AJ7: =SUMIFS(技术配置!I:I,技术配置!F:F,$D7) -> 36 | AK7: =SUMIFS(技术配置!L:L,技术配置!F:F,$D7) -> 102.6 | AL7: =SUMIFS(技术配置!M:M,技术配置!F:F,$D7) -> 96.79 | AM7: 115.176 | AN7: =AM7/I7 -> 1.7088427
A8: 技术部 | B8: 经验反馈改进 | C8: 经验反馈改进 | D8: PRJ-JS-经验-2024-001 | E8: 已签订 | F8: XX能源集团 | G8: 0.06 | H8: 78.23 | I8: 73.8 | J8: 5.71 | K8: 其中： | L8: 5 | M8: 0.06 | N8: 60 | O8: 3.71 | P8: 2 | Q8: 71.012 | R8: 其中： | S8: 2.952 | T8: 0.19 | U8: 0 | V8: 0.1 | W8: 0.1 | X8: 0.08 | Y8: 0.29 | Z8: 5.7 | AA8: 4.75 | AB8: 0.19 | AC8: 0.06 | AD8: 0 | AE8: 0 | AF8: 0 | AG8: 0 | AH8: 0 | AI8: 0 | AJ8: =SUMIFS(技术配置!I:I,技术配置!F:F,$D8) -> 30 | AK8: =SUMIFS(技术配置!L:L,技术配置!F:F,$D8) -> 60 | AL8: =SUMIFS(技术配置!M:M,技术配置!F:F,$D8) -> 56.6 | AM8: 76.722 | AN8: =AM8/I8 -> 1.0395935
A9: 技术部 | B9: 经验反馈改进 | C9: 经验反馈改进 | D9: PRJ-JS-经验-2025-002 | E9: 已签订 | F9: XX能源集团 | G9: 0.06 | H9: 74.31 | I9: 70.1 | J9: 5.59 | K9: 其中： | L9: 5 | M9: 0.06 | N9: 60 | O9: 3.63 | P9: 1.96 | Q9: 75.164 | R9: 其中： | S9: 2.804 | T9: 0.19 | U9: 0 | V9: 0.09 | W9: 0.09 | X9: 0.07 | Y9: 0.28 | Z9: 5.6 | AA9: 4.66 | AB9: 0.19 | AC9: 0.06 | AD9: 0 | AE9: 0 | AF9: 0 | AG9: 0 | AH9: 0 | AI9: 0 | AJ9: =SUMIFS(技术配置!I:I,技术配置!F:F,$D9) -> 30 | AK9: =SUMIFS(技术配置!L:L,技术配置!F:F,$D9) -> 64.8 | AL9: =SUMIFS(技术配置!M:M,技术配置!F:F,$D9) -> 61.13 | AM9: 80.754 | AN9: =AM9/I9 -> 1.1519829
A10: 技术部 | B10: 经验反馈改进 | C10: 经验反馈改进 | D10: PRJ-JS-经验-2025-003 | E10: 已签订 | F10: XX能源集团 | G10: 0.06 | H10: 73.35 | I10: 69.2 | J10: 5.52 | K10: 其中： | L10: 5 | M10: 0.06 | N10: 60 | O10: 3.59 | P10: 1.93 | Q10: 76.928 | R10: 其中： | S10: 2.768 | T10: 0.18 | U10: 0 | V10: 0.09 | W10: 0.09 | X10: 0.07 | Y10: 0.28 | Z10: 5.5 | AA10: 4.6 | AB10: 0.18 | AC10: 0.06 | AD10: 0 | AE10: 0 | AF10: 0 | AG10: 0 | AH10: 0 | AI10: 0 | AJ10: =SUMIFS(技术配置!I:I,技术配置!F:F,$D10) -> 30 | AK10: =SUMIFS(技术配置!L:L,技术配置!F:F,$D10) -> 66.9 | AL10: =SUMIFS(技术配置!M:M,技术配置!F:F,$D10) -> 63.11 | AM10: 82.448 | AN10: =AM10/I10 -> 1.1914451
A11: 技术部 | B11: 新技术应用 | C11: 新技术应用 | D11: PRJ-JS-新技-2024-001 | E11: 已签订 | F11: XX能源集团 | G11: 0.06 | H11: 68.48 | I11: 64.6 | J11: 5.1 | K11: 其中： | L11: 5 | M11: 0.06 | N11: 60 | O11: 3.31 | P11: 1.78 | Q11: 123.554 | R11: 其中： | S11: 2.584 | T11: 0.17 | U11: 0 | V11: 0.09 | W11: 0.09 | X11: 0.07 | Y11: 0.26 | Z11: 5.1 | AA11: 4.25 | AB11: 0.17 | AC11: 0.05 | AD11: 0 | AE11: 0 | AF11: 0 | AG11: 0 | AH11: 0 | AI11: 0 | AJ11: =SUMIFS(技术配置!I:I,技术配置!F:F,$D11) -> 36 | AK11: =SUMIFS(技术配置!L:L,技术配置!F:F,$D11) -> 117.36 | AL11: =SUMIFS(技术配置!M:M,技术配置!F:F,$D11) -> 110.72 | AM11: 128.654 | AN11: =AM11/I11 -> 1.991548
A12: 技术部 | B12: 新技术应用 | C12: 新技术应用 | D12: PRJ-JS-新技-2025-002 | E12: 已签订 | F12: XX能源集团 | G12: 0.06 | H12: 81.83 | I12: 77.2 | J12: 6.07 | K12: 其中： | L12: 5 | M12: 0.07 | N12: 60 | O12: 3.95 | P12: 2.12 | Q12: 120.558 | R12: 其中： | S12: 3.088 | T12: 0.2 | U12: 0 | V12: 0.1 | W12: 0.1 | X12: 0.08 | Y12: 0.3 | Z12: 6.1 | AA12: 5.05 | AB12: 0.2 | AC12: 0.06 | AD12: 0 | AE12: 0 | AF12: 0 | AG12: 0 | AH12: 0 | AI12: 0 | AJ12: =SUMIFS(技术配置!I:I,技术配置!F:F,$D12) -> 36 | AK12: =SUMIFS(技术配置!L:L,技术配置!F:F,$D12) -> 111.6 | AL12: =SUMIFS(技术配置!M:M,技术配置!F:F,$D12) -> 105.28 | AM12: 126.628 | AN12: =AM12/I12 -> 1.6402591
A13: 技术部 | B13: 新技术应用 | C13: 新技术应用 | D13: PRJ-JS-新技-2025-003 | E13: 已签订 | F13: XX能源集团 | G13: 0.06 | H13: 64.13 | I13: 60.5 | J13: 4.84 | K13: 其中： | L13: 5 | M13: 0.05 | N13: 60 | O13: 3.15 | P13: 1.69 | Q13: 108.53 | R13: 其中： | S13: 2.42 | T13: 0.16 | U13: 0 | V13: 0.08 | W13: 0.08 | X13: 0.06 | Y13: 0.24 | Z13: 4.8 | AA13: 4.03 | AB13: 0.16 | AC13: 0.05 | AD13: 0 | AE13: 0 | AF13: 0 | AG13: 0 | AH13: 0 | AI13: 0 | AJ13: =SUMIFS(技术配置!I:I,技术配置!F:F,$D13) -> 36 | AK13: =SUMIFS(技术配置!L:L,技术配置!F:F,$D13) -> 102.24 | AL13: =SUMIFS(技术配置!M:M,技术配置!F:F,$D13) -> 96.45 | AM13: 113.37 | AN13: =AM13/I13 -> 1.8738843
... A22: 安全运行部 | B22: 安全评估 | C22: 安全评估 | D22: PRJ-AQ-安全-2025-003 | E22: 已签订 | F22: XX能源集团 | G22: 0.06 | H22: 62.54 | I22: 59 | J22: 7.2 | K22: 其中： | L22: 5 | M22: 0.08 | N22: 60 | O22: 4.68 | P22: 2.52 | Q22: 60.73 | R22: 其中： | S22: 2.36 | T22: 0.24 | U22: 0 | V22: 0.12 | W22: 0.12 | X22: 0.1 | Y22: 0.36 | Z22: 7.2 | AA22: 6 | AB22: 0.24 | AC22: 0.07 | AD22: 0 | AE22: 0 | AF22: 0 | AG22: 0 | AH22: 0 | AI22: 0 | AJ22: =SUMIFS(技术配置!I:I,技术配置!F:F,$D22) -> 24 | AK22: =SUMIFS(技术配置!L:L,技术配置!F:F,$D22) -> 46.56 | AL22: =SUMIFS(技术配置!M:M,技术配置!F:F,$D22) -> 43.92 | AM22: 67.93 | AN22: =AM22/I22 -> 1.1513559

Sheet 部门公共费用明细
A1: 部门 | B1: 预算二级科目 | C1: 业务内容 | D1: 计算依据 | E1: 税率 | F1: 年度预算(含税) | G1: 年度预算(净额)
A2: 安全运行部 | B2: 办公费 | C2: 日常办公 | D2: 按人均 | E2: 0.06 | F2: 2.5 | G2: 2.36
A3: 安全运行部 | B3: 培训费 | C3: 技能培训 | D3: 按计划 | E3: 0.06 | F3: 1.5 | G3: 1.42
A4: 安全运行部 | B4: 水费 | C4: 办公用水 | D4: 按上年 | E4: 0.06 | F4: 0.5 | G4: 0.47
A5: 安全运行部 | B5: 电费 | C5: 办公用电 | D5: 按上年 | E5: 0.06 | F5: 0.8 | G5: 0.75
A6: 技术部 | B6: 办公费 | C6: 日常办公 | D6: 按人均 | E6: 0.06 | F6: 2.5 | G6: 2.36
A7: 技术部 | B7: 培训费 | C7: 技能培训 | D7: 按计划 | E7: 0.06 | F7: 1.5 | G7: 1.42
A8: 技术部 | B8: 水费 | C8: 办公用水 | D8: 按上年 | E8: 0.06 | F8: 0.5 | G8: 0.47
A9: 技术部 | B9: 电费 | C9: 办公用电 | D9: 按上年 | E9: 0.06 | F9: 0.8 | G9: 0.75
A10: 设备管理部 | B10: 办公费 | C10: 日常办公 | D10: 按人均 | E10: 0.06 | F10: 2.5 | G10: 2.36
A11: 设备管理部 | B11: 培训费 | C11: 技能培训 | D11: 按计划 | E11: 0.06 | F11: 1.5 | G11: 1.42
A12: 设备管理部 | B12: 水费 | C12: 办公用水 | D12: 按上年 | E12: 0.06 | F12: 0.5 | G12: 0.47
A13: 设备管理部 | B13: 电费 | C13: 办公用电 | D13: 按上年 | E13: 0.06 | F13: 0.8 | G13: 0.75

Sheet 技术配置
A1: 部门（*） | B1: 预算二级科目（*） | C1: 配置人员分类（*） | D1: 级别（*） | E1: 项目名称（*） | F1: 项目号（*） | G1: 人数 | H1: 供应商（*） | I1: 服务人月 | J1: 单价（元） | K1: 税率（*） | L1: 年度预算（含税）-万元 | M1: 年度预算（净额）-万元 | N1: 平均单价（万元/月）
A2: 设备管理部 | B2: 业务支持费-技术配置 | C2: 技术服务 | D2: 初级 | E2: 设备维护 | F2: PRJ-SB-设备-2024-001 | G2: 2 | H2: 供应商1 | I2: 12 | J2: 11200 | K2: 0.06 | L2: 13.44 | M2: 12.68 | N2: 1.06
A3: 设备管理部 | B3: 业务支持费-技术配置 | C3: 技术服务 | D3: 初级 | E3: 设备维护 | F3: PRJ-SB-设备-2025-002 | G3: 2 | H3: 供应商2 | I3: 12 | J3: 11000 | K3: 0.06 | L3: 13.2 | M3: 12.45 | N3: 1.04
A4: 设备管理部 | B4: 业务支持费-技术配置 | C4: 技术服务 | D4: 初级 | E4: 设备维护 | F4: PRJ-SB-设备-2025-003 | G4: 2 | H4: 供应商3 | I4: 12 | J4: 11000 | K4: 0.06 | L4: 13.2 | M4: 12.45 | N4: 1.04
A5: 技术部 | B5: 业务支持费-技术配置 | C5: 技术服务 | D5: 专家 | E5: 热能动力研究 | F5: PRJ-JS-热能-2024-001 | G5: 5 | H5: 供应商2 | I5: 36 | J5: 31100 | K5: 0.06 | L5: 111.96 | M5: 105.62 | N5: 2.93
A6: 技术部 | B6: 业务支持费-技术配置 | C6: 技术服务 | D6: 专家 | E6: 热能动力研究 | F6: PRJ-JS-热能-2025-002 | G6: 5 | H6: 供应商1 | I6: 36 | J6: 29400 | K6: 0.06 | L6: 105.84 | M6: 99.85 | N6: 2.77
A7: 技术部 | B7: 业务支持费-技术配置 | C7: 技术服务 | D7: 专家 | E7: 热能动力研究 | F7: PRJ-JS-热能-2025-003 | G7: 5 | H7: 供应商1 | I7: 36 | J7: 28500 | K7: 0.06 | L7: 102.6 | M7: 96.79 | N7: 2.69
A8: 技术部 | B8: 业务支持费-技术配置 | C8: 技术服务 | D8: 高级 | E8: 经验反馈改进 | F8: PRJ-JS-经验-2024-001 | G8: 4 | H8: 供应商3 | I8: 30 | J8: 20000 | K8: 0.06 | L8: 60 | M8: 56.6 | N8: 1.89
A9: 技术部 | B9: 业务支持费-技术配置 | C9: 技术服务 | D9: 高级 | E9: 经验反馈改进 | F9: PRJ-JS-经验-2025-002 | G9: 4 | H9: 供应商1 | I9: 30 | J9: 21600 | K9: 0.06 | L9: 64.8 | M9: 61.13 | N9: 2.04
A10: 技术部 | B10: 业务支持费-技术配置 | C10: 技术服务 | D10: 高级 | E10: 经验反馈改进 | F10: PRJ-JS-经验-2025-003 | G10: 4 | H10: 供应商2 | I10: 30 | J10: 22300 | K10: 0.06 | L10: 66.9 | M10: 63.11 | N10: 2.1
A11: 技术部 | B11: 业务支持费-技术配置 | C11: 技术服务 | D11: 专家 | E11: 新技术应用 | F11: PRJ-JS-新技-2024-001 | G11: 5 | H11: 供应商2 | I11: 36 | J11: 32599 | K11: 0.06 | L11: 117.36 | M11: 110.72 | N11: 3.08
A12: 技术部 | B12: 业务支持费-技术配置 | C12: 技术服务 | D12: 专家 | E12: 新技术应用 | F12: PRJ-JS-新技-2025-002 | G12: 5 | H12: 供应商2 | I12: 36 | J12: 31000 | K12: 0.06 | L12: 111.6 | M12: 105.28 | N12: 2.92
A13: 技术部 | B13: 业务支持费-技术配置 | C13: 技术服务 | D13: 专家 | E13: 新技术应用 | F13: PRJ-JS-新技-2025-003 | G13: 5 | H13: 供应商1 | I13: 36 | J13: 28400 | K13: 0.06 | L13: 102.24 | M13: 96.45 | N13: 2.68
... A22: 安全运行部 | B22: 业务支持费-技术配置 | C22: 技术服务 | D22: 中级 | E22: 安全评估 | F22: PRJ-AQ-安全-2025-003 | G22: 3 | H22: 供应商2 | I22: 24 | J22: 19400 | K22: 0.06 | L22: 46.56 | M22: 43.92 | N22: 1.83
